nengo_extras/__init__.py
nengo_extras/camera.py
nengo_extras/compat.py
nengo_extras/convnet.py
nengo_extras/cuda_convnet.py
nengo_extras/data.py
nengo_extras/deepnetworks.py
nengo_extras/deepview.py
nengo_extras/dists.py
nengo_extras/gexf.py
nengo_extras/graphviz.py
nengo_extras/gui.py
nengo_extras/keras.py
nengo_extras/learning_rules.py
nengo_extras/loihi_training.py
nengo_extras/matplotlib.py
nengo_extras/neurons.py
nengo_extras/ocl.py
nengo_extras/plot_spikes.py
nengo_extras/probe.py
nengo_extras/rc.py
nengo_extras/reqs.py
nengo_extras/simulators.py
nengo_extras/version.py
nengo_extras/vision.py
nengo_extras/networks/__init__.py
nengo_extras/networks/matrix_multiplication.py
nengo_extras/networks/product.py
nengo_extras/networks/tests/__init__.py
nengo_extras/networks/tests/test_matrix_multiplication.py
nengo_extras/networks/tests/test_product.py
nengo_extras/spa/__init__.py
nengo_extras/spa/utils.py
nengo_extras/spa/tests/__init__.py
nengo_extras/spa/tests/test_utils.py
nengo_extras/tests/__init__.py
nengo_extras/tests/test_convnet.py
nengo_extras/tests/test_data.py
nengo_extras/tests/test_dists.py
nengo_extras/tests/test_examples.py
nengo_extras/tests/test_gexf.py
nengo_extras/tests/test_graphviz.py
nengo_extras/tests/test_keras.py
nengo_extras/tests/test_learning_rules.py
nengo_extras/tests/test_loihi_training.py
nengo_extras/tests/test_matplotlib.py
nengo_extras/tests/test_neurons.py
nengo_extras/tests/test_plot_spikes.py
nengo_extras/tests/test_probe.py
nengo_extras/tests/test_simulators.py
nengo_extras-0.5.0.dist-info/LICENSE.rst
nengo_extras-0.5.0.dist-info/METADATA
nengo_extras-0.5.0.dist-info/WHEEL
nengo_extras-0.5.0.dist-info/top_level.txt
nengo_extras-0.5.0.dist-info/RECORD
