Metadata-Version: 2.1
Name: nengo-extras
Version: 0.5.0
Summary: Lesser used features for the Nengo neural simulator
Home-page: https://www.nengo.ai/nengo-extras
Author: Applied Brain Research
Author-email: info@appliedbrainresearch.com
License: Free for non-commercial use
Platform: UNKNOWN
Classifier: Intended Audience :: Science/Research
Classifier: License :: Free for non-commercial use
Classifier: Operating System :: OS Independent
Classifier: Programming Language :: Python :: 3.6
Classifier: Programming Language :: Python :: 3.7
Classifier: Programming Language :: Python :: 3.8
Classifier: Programming Language :: Python :: 3.9
Classifier: Topic :: Scientific/Engineering :: Artificial Intelligence
Requires-Python: >=3.6
License-File: LICENSE.rst
Requires-Dist: numpy (>=1.8)
Requires-Dist: nengo (>=3.0)
Requires-Dist: matplotlib (>=1.4)
Requires-Dist: pillow
Provides-Extra: all
Requires-Dist: sphinx (>=1.8) ; extra == 'all'
Requires-Dist: numpydoc (>=0.6) ; extra == 'all'
Requires-Dist: nengo-sphinx-theme (>=1.2.0) ; extra == 'all'
Requires-Dist: nbsphinx (>=0.8.8) ; extra == 'all'
Requires-Dist: tensorflow ; extra == 'all'
Requires-Dist: jupyter ; extra == 'all'
Requires-Dist: nengo-dl ; extra == 'all'
Requires-Dist: keras ; extra == 'all'
Requires-Dist: numba (>=0.43.1) ; extra == 'all'
Requires-Dist: scipy ; extra == 'all'
Requires-Dist: pytest (>=6.0) ; extra == 'all'
Requires-Dist: pytest-allclose ; extra == 'all'
Requires-Dist: pytest-plt ; extra == 'all'
Requires-Dist: pytest-rng ; extra == 'all'
Provides-Extra: docs
Requires-Dist: sphinx (>=1.8) ; extra == 'docs'
Requires-Dist: numpydoc (>=0.6) ; extra == 'docs'
Requires-Dist: nengo-sphinx-theme (>=1.2.0) ; extra == 'docs'
Requires-Dist: nbsphinx (>=0.8.8) ; extra == 'docs'
Requires-Dist: tensorflow ; extra == 'docs'
Requires-Dist: jupyter ; extra == 'docs'
Provides-Extra: optional
Requires-Dist: nengo-dl ; extra == 'optional'
Requires-Dist: keras ; extra == 'optional'
Requires-Dist: tensorflow ; extra == 'optional'
Requires-Dist: numba (>=0.43.1) ; extra == 'optional'
Requires-Dist: scipy ; extra == 'optional'
Provides-Extra: tests
Requires-Dist: jupyter ; extra == 'tests'
Requires-Dist: pytest (>=6.0) ; extra == 'tests'
Requires-Dist: pytest-allclose ; extra == 'tests'
Requires-Dist: pytest-plt ; extra == 'tests'
Requires-Dist: pytest-rng ; extra == 'tests'
